[
	{
		"name": "Pirate",
		"uniqueTo": "Pirates",
		"replaces": "Musketman",
		"unitType": "Gunpowder",
		"movement": 2,
		"strength": 24,
		"cost": 130,
		"promotions": ["Amphibious"],
		"uniques": ["No movement cost to pillage"],
		"requiredTech": "Gunpowder",
		"upgradesTo": "Rifleman",
		"obsoleteTech": "Rifling",
		"attackSound": "shot"
	},
	{
		"name": "Captain",
		"uniqueTo": "Pirates",
		"replaces": "Great Admiral",
		"unitType": "Civilian Water",
		"uniques": [
            // TODO: "[Every adjacent [{Friendly} {Water}] unit] heals [100] HP <by consuming this unit>",
			"All adjacent units heal [+15] HP when healing",
            "May Paradrop to [{your} {Coastal} {City center}] tiles up to [25] tiles away <in [City center] tiles>", // Change Port
            "[+15]% Strength bonus for [{Military} {Water}] units within [2] tiles",
			"Can be earned through combat <for [Water] units>",
            "Is part of Great Person group [Admiral]",
            "Great Person - [War]", "Unbuildable", "Uncapturable"],
		"movement": 4
	}
]
